[
  {
      "name": "시금치",
      "scientific_name": "Spinacia oleracea",
      "image_url": "/assets/images/plants/시금치.jpg",
      "growing_zone": "4-9",
      "max_height": "30 cm",
      "max_width": "20 cm",
      "sunlight_requirements": "부분 햇빛에서 완전한 햇빛",
      "sunlight_requirements_percent": 75,
      "water_requirements": "중간",
      "water_requirements_percent": 50,
      "soil_type": "양토",
      "pH_range": "7.0-8.0",
      "pH_range_percent": 80,
      "planting_time": {"months": [3, 4, 7, 9]},
      "harvest_time": "봄",
      "optimal_temperature": {"low": 15, "high": 20},
      "germination_period_percent": 50,
      "growth_rate_percent": 80,
      "common_pests": ["진딧물", "달팽이"],
      "pest_control_methods": ["니임 오일", "맥주 덫"],
      "companion_plants": ["당근", "무"],
      "incompatible_plants": ["브로콜리"],
      "special_care_tips": "쓴맛을 방지하기 위해 충분한 물 공급",
      "regional_info": "서늘한 기온을 선호",
      "reference_link": "https://www.nongsaro.go.kr/portal/ps/psz/psza/contentSub.ps?menuId=PS03172&pageIndex=1&pageSize=10&sSeCode=335001&cntntsNo=101618&sType=sCntntsSj&sText=%EC%8B%9C%EA%B8%88%EC%B9%98"
  },
  {
      "name": "배추",
      "scientific_name": "Brassica rapa subsp. pekinensis",
      "image_url": "/assets/images/plants/배추.jpg",
      "growing_zone": "6-9",
      "max_height": "40 cm",
      "max_width": "30 cm",
      "sunlight_requirements": "완전한 햇빛",
      "sunlight_requirements_percent": 100,
      "water_requirements": "중간",
      "water_requirements_percent": 50,
      "soil_type": "양토",
      "pH_range": "6.5-7.5",
      "pH_range_percent": 85,
      "planting_time": {"months": [3, 5, 7, 9]},
      "harvest_time": "늦가을",
      "optimal_temperature": {"low": 15, "high": 20},
      "germination_period_percent": 75,
      "growth_rate_percent": 80,
      "common_pests": ["진딧물", "배추벌레"],
      "pest_control_methods": ["니임 오일", "손으로 잡기"],
      "companion_plants": ["당근", "양파"],
      "incompatible_plants": ["토마토"],
      "special_care_tips": "볼팅을 방지하기 위해 일관된 수분 공급",
      "regional_info": "서늘한 기후에서 잘 자람",
      "reference_link": "https://www.nongsaro.go.kr/portal/ps/psz/psza/contentSub.ps?menuId=PS03172&pageIndex=1&pageSize=10&sSeCode=335001&cntntsNo=101627&sType=sCntntsSj&sText=%EB%B0%B0%EC%B6%94"
  },
  {
      "name": "무",
      "scientific_name": "Raphanus sativus",
      "image_url": "/assets/images/plants/무.jpg",
      "growing_zone": "6-9",
      "max_height": "30 cm",
      "max_width": "15 cm",
      "sunlight_requirements": "완전한 햇빛",
      "sunlight_requirements_percent": 100,
      "water_requirements": "중간",
      "water_requirements_percent": 50,
      "soil_type": "양토, 사질토",
      "pH_range": "6.0-7.0",
      "pH_range_percent": 70,
      "planting_time": {"months": [3, 4, 5, 6, 7, 8, 9]},
      "harvest_time": "가을",
      "optimal_temperature": {"low": 17, "high": 23},
      "germination_period_percent": 75,
      "growth_rate_percent": 80,
      "common_pests": ["벼룩벌레", "뿌리 구더기"],
      "pest_control_methods": ["행커버", "작물 교대"],
      "companion_plants": ["상추", "오이"],
      "incompatible_plants": ["감자"],
      "special_care_tips": "묘목이 너무 빽빽하지 않도록 간격을 유지",
      "regional_info": "온화한 기후에서 잘 자람",
      "reference_link": "https://www.nongsaro.go.kr/portal/ps/psz/psza/contentSub.ps?menuId=PS03172&pageIndex=1&pageSize=10&sSeCode=335001&cntntsNo=101626&sType=sCntntsSj&sText=%EB%AC%B4"
  },
  {
      "name": "브로콜리",
      "scientific_name": "Brassica oleracea var. italica",
      "image_url": "/assets/images/plants/브로콜리.jpg",
      "growing_zone": "4-9",
      "max_height": "60 cm",
      "max_width": "45 cm",
      "sunlight_requirements": "완전한 햇빛",
      "sunlight_requirements_percent": 100,
      "water_requirements": "중간",
      "water_requirements_percent": 50,
      "soil_type": "양토",
      "pH_range": "6.0-7.5",
      "pH_range_percent": 80,
      "planting_time": {"months": [1,3,8,9]},
      "harvest_time": "봄, 가을",
      "optimal_temperature": {"low": 15, "high": 20},
      "germination_period_percent": 75,
      "growth_rate_percent": 80,
      "common_pests": ["진딧물", "배추벌레"],
      "pest_control_methods": ["니임 오일", "손으로 잡기"],
      "companion_plants": ["상추", "시금치"],
      "incompatible_plants": ["토마토"],
      "special_care_tips": "꾸준한 물 공급이 중요",
      "regional_info": "서늘한 기후에서 잘 자람",
      "reference_link": "https://www.nongsaro.go.kr/portal/ps/psz/psza/contentSub.ps?menuId=PS03172&pageIndex=1&pageSize=10&sSeCode=335001&cntntsNo=101615&sType=sCntntsSj&sText=%EB%B8%8C%EB%A1%9C%EC%BD%9C%EB%A6%AC"
  },
  {
    "name": "상추",
    "scientific_name": "Lactuca sativa",
    "image_url": "/assets/images/plants/상추.jpg",
    "growing_zone": "4-9",
    "max_height": "30 cm",
    "max_width": "25 cm",
    "sunlight_requirements": "부분 햇빛에서 완전한 햇빛",
    "sunlight_requirements_percent": 75,
    "water_requirements": "중간",
    "water_requirements_percent": 60,
    "soil_type": "양토",
    "pH_range": "6.0-7.0",
    "pH_range_percent": 85,
    "planting_time": {"months": [4, 5, 6, 7, 8, 9]},
    "harvest_time": "봄",
    "optimal_temperature": {"low": 10, "high": 20},
    "germination_period_percent": 70,
    "growth_rate_percent": 75,
    "common_pests": ["진딧물", "달팽이"],
    "pest_control_methods": ["니임 오일", "비누 스프레이"],
    "companion_plants": ["당근", "시금치"],
    "incompatible_plants": ["브로콜리"],
    "special_care_tips": "상추는 자주 수확하여 재배를 촉진",
    "regional_info": "서늘한 기온을 선호",
    "reference_link": "https://www.nongsaro.go.kr/portal/ps/psz/psza/contentMain.ps?menuId=PS03172&pageIndex=1&pageSize=10&sSeCode=335001&cntntsNo=&sType=sCntntsSj&sText=%EC%83%81%EC%B6%94#1"
  },
  {
    "name": "당근",
    "scientific_name": "Daucus carota",
    "image_url": "/assets/images/plants/당근.jpg",
    "growing_zone": "4-10",
    "max_height": "30 cm",
    "max_width": "10 cm",
    "sunlight_requirements": "완전한 햇빛",
    "sunlight_requirements_percent": 100,
    "water_requirements": "중간",
    "water_requirements_percent": 50,
    "soil_type": "양토",
    "pH_range": "6.0-7.0",
    "pH_range_percent": 85,
    "planting_time": {"months": [3, 4, 5, 7, 8]},
    "harvest_time": "여름",
    "optimal_temperature": {"low": 15, "high": 25},
    "germination_period_percent": 60,
    "growth_rate_percent": 70,
    "common_pests": ["당근파리", "진딧물"],
    "pest_control_methods": ["니임 오일", "로테논"],
    "companion_plants": ["상추", "시금치"],
    "incompatible_plants": ["셀러리"],
    "special_care_tips": "토양이 잘 배수되고 부드럽게 유지",
    "regional_info": "배수가 잘 되는 토양을 선호",
    "reference_link": "https://www.nongsaro.go.kr/portal/ps/psz/psza/contentMain.ps?menuId=PS03172&pageIndex=1&pageSize=10&sSeCode=335001&cntntsNo=&sType=sCntntsSj&sText=%EB%8B%B9%EA%B7%BC#1"
  },
  {
    "name": "케일",
    "scientific_name": "Brassica oleracea var. sabellica",
    "image_url": "/assets/images/plants/케일.jpg",
    "growing_zone": "3-9",
    "max_height": "60 cm",
    "max_width": "30 cm",
    "sunlight_requirements": "부분 햇빛에서 완전한 햇빛",
    "sunlight_requirements_percent": 75,
    "water_requirements": "중간",
    "water_requirements_percent": 55,
    "soil_type": "양토",
    "pH_range": "6.0-7.5",
    "pH_range_percent": 85,
    "planting_time": {"months": [3]},
    "harvest_time": "봄",
    "optimal_temperature": {"low": 10, "high": 20},
    "germination_period_percent": 60,
    "growth_rate_percent": 80,
    "common_pests": ["배추벌레", "진딧물"],
    "pest_control_methods": ["니임 오일", "BT 살포"],
    "companion_plants": ["당근", "양파"],
    "incompatible_plants": ["토마토"],
    "special_care_tips": "잎이 부드럽게 유지되도록 꾸준히 물 공급",
    "regional_info": "서늘한 기온을 선호",
    "reference_link": "https://www.gardeningknowhow.com/edible/vegetables/kale/growing-kale.htm"
  },
  {
    "name": "양파",
    "scientific_name": "Allium cepa",
    "image_url": "/assets/images/plants/양파.jpg",
    "growing_zone": "3-9",
    "max_height": "45 cm",
    "max_width": "10 cm",
    "sunlight_requirements": "완전한 햇빛",
    "sunlight_requirements_percent": 100,
    "water_requirements": "중간",
    "water_requirements_percent": 60,
    "soil_type": "양토",
    "pH_range": "6.0-7.0",
    "pH_range_percent": 85,
    "planting_time": {"months": [3, 8, 9]},
    "harvest_time": "여름",
    "optimal_temperature": {"low": 10, "high": 25},
    "germination_period_percent": 70,
    "growth_rate_percent": 75,
    "common_pests": ["양파벌레", "진딧물"],
    "pest_control_methods": ["니임 오일", "파리 덫"],
    "companion_plants": ["당근", "시금치"],
    "incompatible_plants": ["콩"],
    "special_care_tips": "토양이 건조하지 않도록 물을 충분히 공급",
    "regional_info": "서늘한 기온에서 잘 자람",
    "reference_link": "https://www.nongsaro.go.kr/portal/ps/psz/psza/contentSub.ps?menuId=PS03172&pageIndex=1&pageSize=10&sSeCode=335001&cntntsNo=101643&sType=sCntntsSj&sText=%EC%96%91%ED%8C%8C"
  },
  {
    "name": "감자",
    "scientific_name": "Solanum tuberosum",
    "image_url": "/assets/images/plants/감자.jpg",
    "growing_zone": "3-10",
    "max_height": "60 cm",
    "max_width": "45 cm",
    "sunlight_requirements": "완전한 햇빛",
    "sunlight_requirements_percent": 100,
    "water_requirements": "중간",
    "water_requirements_percent": 70,
    "soil_type": "양토",
    "pH_range": "5.5-7.0",
    "pH_range_percent": 75,
    "planting_time": {"months": [2,4,8,1]},
    "harvest_time": "여름",
    "optimal_temperature": {"low": 10, "high": 25},
    "germination_period_percent": 60,
    "growth_rate_percent": 80,
    "common_pests": ["감자벌레", "진딧물"],
    "pest_control_methods": ["니임 오일", "BT 살포"],
    "companion_plants": ["양파", "콩"],
    "incompatible_plants": ["토마토"],
    "special_care_tips": "싹이 나오기 전까지는 물을 많이 주지 않음",
    "regional_info": "서늘한 기온에서 잘 자람",
    "reference_link": "https://www.nongsaro.go.kr/portal/ps/psz/psza/contentSub.ps?menuId=PS03172&pageIndex=1&pageSize=10&sSeCode=335001&cntntsNo=101612&sType=sCntntsSj&sText=%EA%B0%90%EC%9E%90"
  },
  {
    "name": "완두콩",
    "scientific_name": "Pisum sativum",
    "image_url": "/assets/images/plants/완두콩.jpg",
    "growing_zone": "3-11",
    "max_height": "60 cm",
    "max_width": "30 cm",
    "sunlight_requirements": "부분 햇빛에서 완전한 햇빛",
    "sunlight_requirements_percent": 85,
    "water_requirements": "중간",
    "water_requirements_percent": 50,
    "soil_type": "양토",
    "pH_range": "6.0-7.5",
    "pH_range_percent": 80,
    "planting_time": {"months": [3, 10]},
    "harvest_time": "여름",
    "optimal_temperature": {"low": 10, "high": 20},
    "germination_period_percent": 70,
    "growth_rate_percent": 75,
    "common_pests": ["완두콩벌레", "진딧물"],
    "pest_control_methods": ["니임 오일", "파리 덫"],
    "companion_plants": ["감자", "당근"],
    "incompatible_plants": ["양파"],
    "special_care_tips": "줄기를 지지할 수 있도록 지지대 사용",
    "regional_info": "서늘한 기온에서 잘 자람",
    "reference_link": "https://www.nongsaro.go.kr/portal/ps/psz/psza/contentSub.ps?menuId=PS03172&pageIndex=1&pageSize=10&sSeCode=335001&cntntsNo=228670&sType=sCntntsSj&sText=%EC%99%84%EB%91%90"
  },
  {
    "name": "콜리플라워",
    "scientific_name": "Brassica oleracea var. botrytis",
    "image_url": "/assets/images/plants/콜리플라워.jpg",
    "growing_zone": "2-10",
    "max_height": "60 cm",
    "max_width": "50 cm",
    "sunlight_requirements": "부분 햇빛에서 완전한 햇빛",
    "sunlight_requirements_percent": 75,
    "water_requirements": "중간",
    "water_requirements_percent": 60,
    "soil_type": "양토",
    "pH_range": "6.0-7.5",
    "pH_range_percent": 80,
    "planting_time": {"months": [5, 7]},
    "harvest_time": "여름",
    "optimal_temperature": {"low": 15, "high": 25},
    "germination_period_percent": 65,
    "growth_rate_percent": 70,
    "common_pests": ["배추벌레", "진딧물"],
    "pest_control_methods": ["니임 오일", "BT 살포"],
    "companion_plants": ["양파", "당근"],
    "incompatible_plants": ["토마토"],
    "special_care_tips": "잎과 줄기가 부드럽게 유지되도록 꾸준히 물 공급",
    "regional_info": "서늘한 기온을 선호",
    "reference_link": "https://www.gardeningknowhow.com/edible/vegetables/cauliflower/growing-cauliflower.htm"
  },
  {
    "name": "토마토",
    "scientific_name": "Solanum lycopersicum",
    "image_url": "/assets/images/plants/토마토.jpg",
    "growing_zone": "4-11",
    "max_height": "180 cm",
    "max_width": "60 cm",
    "sunlight_requirements": "완전한 햇빛",
    "sunlight_requirements_percent": 100,
    "water_requirements": "중간",
    "water_requirements_percent": 70,
    "soil_type": "양토",
    "pH_range": "6.0-6.8",
    "pH_range_percent": 85,
    "planting_time": {"months": [3, 4]},
    "harvest_time": "여름",
    "optimal_temperature": {"low": 15, "high": 30},
    "germination_period_percent": 80,
    "growth_rate_percent": 85,
    "common_pests": ["진딧물", "토마토 벌레"],
    "pest_control_methods": ["니임 오일", "BT 살포"],
    "companion_plants": ["바질", "양파"],
    "incompatible_plants": ["감자"],
    "special_care_tips": "지지대나 케이지를 사용해 지지",
    "regional_info": "따뜻한 기온을 선호",
    "reference_link": "https://www.nongsaro.go.kr/portal/ps/psz/psza/contentSub.ps?menuId=PS03172&pageIndex=1&pageSize=10&sSeCode=335001&cntntsNo=101611&sType=sCntntsSj&sText=%ED%86%A0%EB%A7%88%ED%86%A0"
  },
  {
    "name": "호박",
    "scientific_name": "Cucurbita pepo",
    "image_url": "/assets/images/plants/호박.jpg",
    "growing_zone": "3-10",
    "max_height": "60 cm",
    "max_width": "200 cm",
    "sunlight_requirements": "완전한 햇빛",
    "sunlight_requirements_percent": 100,
    "water_requirements": "중간",
    "water_requirements_percent": 60,
    "soil_type": "양토",
    "pH_range": "6.0-7.5",
    "pH_range_percent": 80,
    "planting_time": {"months": [4, 5, 6, 7]},
    "harvest_time": "여름",
    "optimal_temperature": {"low": 20, "high": 30},
    "germination_period_percent": 75,
    "growth_rate_percent": 85,
    "common_pests": ["호박 벌레", "진딧물"],
    "pest_control_methods": ["니임 오일", "파리 덫"],
    "companion_plants": ["옥수수", "완두콩"],
    "incompatible_plants": ["감자"],
    "special_care_tips": "토양이 과도하게 건조하지 않도록 주의",
    "regional_info": "따뜻한 기온을 선호",
    "reference_link": "https://www.nongsaro.go.kr/portal/ps/psz/psza/contentSub.ps?menuId=PS03172&pageIndex=1&pageSize=10&sSeCode=335001&cntntsNo=101625&sType=sCntntsSj&sText=%ED%98%B8%EB%B0%95"
  },
  {
    "name": "가지",
    "scientific_name": "Solanum melongena",
    "image_url": "/assets/images/plants/가지.jpg",
    "growing_zone": "4-11",
    "max_height": "120 cm",
    "max_width": "60 cm",
    "sunlight_requirements": "완전한 햇빛",
    "sunlight_requirements_percent": 100,
    "water_requirements": "중간",
    "water_requirements_percent": 65,
    "soil_type": "양토",
    "pH_range": "6.2-6.8",
    "pH_range_percent": 85,
    "planting_time": {"months": [4, 5, 6, 7]},
    "harvest_time": "여름",
    "optimal_temperature": {"low": 22, "high": 30},
    "germination_period_percent": 75,
    "growth_rate_percent": 80,
    "common_pests": ["진딧물", "가지 벌레"],
    "pest_control_methods": ["니임 오일", "파리 덫"],
    "companion_plants": ["바질", "당근"],
    "incompatible_plants": ["감자"],
    "special_care_tips": "지지대나 케이지를 사용해 지지",
    "regional_info": "따뜻한 기온을 선호",
    "reference_link": "https://www.gardeningknowhow.com/edible/vegetables/eggplant/growing-eggplant.htm"
  },
  {
    "name": "옥수수",
    "scientific_name": "Zea mays",
    "image_url": "/assets/images/plants/옥수수.jpg",
    "growing_zone": "3-11",
    "max_height": "300 cm",
    "max_width": "30 cm",
    "sunlight_requirements": "완전한 햇빛",
    "sunlight_requirements_percent": 100,
    "water_requirements": "중간",
    "water_requirements_percent": 70,
    "soil_type": "양토",
    "pH_range": "6.0-6.8",
    "pH_range_percent": 80,
    "planting_time": {"months": [4]},
    "harvest_time": "여름",
    "optimal_temperature": {"low": 15, "high": 30},
    "germination_period_percent": 75,
    "growth_rate_percent": 85,
    "common_pests": ["옥수수 벌레", "진딧물"],
    "pest_control_methods": ["니임 오일", "BT 살포"],
    "companion_plants": ["호박", "완두콩"],
    "incompatible_plants": ["토마토"],
    "special_care_tips": "작물이 크면 지지대를 사용해 지지",
    "regional_info": "따뜻한 기온을 선호",
    "reference_link": "https://www.nongsaro.go.kr/portal/ps/psz/psza/contentSub.ps?menuId=PS03172&pageIndex=1&pageSize=10&sSeCode=335001&cntntsNo=101621&sType=sCntntsSj&sText=%EC%98%A5%EC%88%98%EC%88%98"
  },
  {
    "name": "피망",
    "scientific_name": "Capsicum annuum",
    "image_url": "/assets/images/plants/피망.jpg",
    "growing_zone": "4-11",
    "max_height": "90 cm",
    "max_width": "60 cm",
    "sunlight_requirements": "완전한 햇빛",
    "sunlight_requirements_percent": 100,
    "water_requirements": "중간",
    "water_requirements_percent": 65,
    "soil_type": "양토",
    "pH_range": "6.0-6.8",
    "pH_range_percent": 80,
    "planting_time": {"months": [4]},
    "harvest_time": "여름",
    "optimal_temperature": {"low": 20, "high": 30},
    "germination_period_percent": 75,
    "growth_rate_percent": 80,
    "common_pests": ["진딧물", "피망 벌레"],
    "pest_control_methods": ["니임 오일", "파리 덫"],
    "companion_plants": ["바질", "양파"],
    "incompatible_plants": ["감자"],
    "special_care_tips": "지지대나 케이지를 사용해 지지",
    "regional_info": "따뜻한 기온을 선호",
    "reference_link": "https://www.gardeningknowhow.com/edible/vegetables/pepper/growing-peppers.htm"
  },
  {
    "name": "오이",
    "scientific_name": "Cucumis sativus",
    "image_url": "/assets/images/plants/오이.jpg",
    "growing_zone": "4-12",
    "max_height": "200 cm",
    "max_width": "60 cm",
    "sunlight_requirements": "완전한 햇빛",
    "sunlight_requirements_percent": 100,
    "water_requirements": "중간",
    "water_requirements_percent": 75,
    "soil_type": "양토",
    "pH_range": "6.0-6.8",
    "pH_range_percent": 80,
    "planting_time": {"months": [5]},
    "harvest_time": "여름",
    "optimal_temperature": {"low": 20, "high": 30},
    "germination_period_percent": 80,
    "growth_rate_percent": 85,
    "common_pests": ["오이벌레", "진딧물"],
    "pest_control_methods": ["니임 오일", "파리 덫"],
    "companion_plants": ["콩", "옥수수"],
    "incompatible_plants": ["감자"],
    "special_care_tips": "지지대나 트렐리스를 사용해 지지",
    "regional_info": "따뜻한 기온을 선호",
    "reference_link": "https://www.gardeningknowhow.com/edible/vegetables/cucumber/growing-cucumbers.htm"
  },
  {
    "name": "강낭콩",
    "scientific_name": "Phaseolus vulgaris",
    "image_url": "/assets/images/plants/강낭콩.jpg",
    "growing_zone": "3-10",
    "max_height": "200 cm",
    "max_width": "30 cm",
    "sunlight_requirements": "완전한 햇빛",
    "sunlight_requirements_percent": 100,
    "water_requirements": "중간",
    "water_requirements_percent": 60,
    "soil_type": "양토",
    "pH_range": "6.0-7.0",
    "pH_range_percent": 85,
    "planting_time": {"months": [5]},
    "harvest_time": "여름",
    "optimal_temperature": {"low": 15, "high": 25},
    "germination_period_percent": 75,
    "growth_rate_percent": 80,
    "common_pests": ["진딧물", "콩벌레"],
    "pest_control_methods": ["니임 오일", "BT 살포"],
    "companion_plants": ["옥수수", "오이"],
    "incompatible_plants": ["양파"],
    "special_care_tips": "지지대나 트렐리스를 사용해 지지",
    "regional_info": "따뜻한 기온을 선호",
    "reference_link": "https://www.gardeningknowhow.com/edible/vegetables/beans/growing-beans.htm"
  },
  {
    "name": "파프리카",
    "scientific_name": "Capsicum annuum",
    "image_url": "/assets/images/plants/파프리카.jpg",
    "growing_zone": "4-11",
    "max_height": "90 cm",
    "max_width": "60 cm",
    "sunlight_requirements": "완전한 햇빛",
    "sunlight_requirements_percent": 100,
    "water_requirements": "중간",
    "water_requirements_percent": 65,
    "soil_type": "양토",
    "pH_range": "6.0-6.8",
    "pH_range_percent": 80,
    "planting_time": {"months": [5, 6]},
    "harvest_time": "여름",
    "optimal_temperature": {"low": 20, "high": 30},
    "germination_period_percent": 75,
    "growth_rate_percent": 80,
    "common_pests": ["진딧물", "파프리카 벌레"],
    "pest_control_methods": ["니임 오일", "파리 덫"],
    "companion_plants": ["바질", "양파"],
    "incompatible_plants": ["감자"],
    "special_care_tips": "지지대나 케이지를 사용해 지지",
    "regional_info": "따뜻한 기온을 선호",
    "reference_link": "https://www.gardeningknowhow.com/edible/vegetables/pepper/growing-peppers.htm"
  },
  {
    "name": "고추",
    "scientific_name": "Capsicum annuum",
    "image_url": "/assets/images/plants/고추.jpg",
    "growing_zone": "5-11",
    "max_height": "120 cm",
    "max_width": "60 cm",
    "sunlight_requirements": "완전한 햇빛",
    "sunlight_requirements_percent": 100,
    "water_requirements": "중간",
    "water_requirements_percent": 70,
    "soil_type": "양토",
    "pH_range": "6.0-6.8",
    "pH_range_percent": 85,
    "planting_time": {"months": [5, 6]},
    "harvest_time": "여름",
    "optimal_temperature": {"low": 20, "high": 30},
    "germination_period_percent": 75,
    "growth_rate_percent": 85,
    "common_pests": ["진딧물", "고추 벌레"],
    "pest_control_methods": ["니임 오일", "BT 살포"],
    "companion_plants": ["바질", "당근"],
    "incompatible_plants": ["감자"],
    "special_care_tips": "지지대나 케이지를 사용해 지지",
    "regional_info": "따뜻한 기온을 선호",
    "reference_link": "https://www.gardeningknowhow.com/edible/vegetables/pepper/growing-hot-peppers.htm"
  },
  {
    "name": "옥수수",
    "scientific_name": "Zea mays",
    "image_url": "/assets/images/plants/옥수수.jpg",
    "growing_zone": "3-11",
    "max_height": "300 cm",
    "max_width": "30 cm",
    "sunlight_requirements": "완전한 햇빛",
    "sunlight_requirements_percent": 100,
    "water_requirements": "중간",
    "water_requirements_percent": 70,
    "soil_type": "양토",
    "pH_range": "6.0-6.8",
    "pH_range_percent": 80,
    "planting_time": {"months": [6]},
    "harvest_time": "가을",
    "optimal_temperature": {"low": 15, "high": 30},
    "germination_period_percent": 75,
    "growth_rate_percent": 85,
    "common_pests": ["옥수수 벌레", "진딧물"],
    "pest_control_methods": ["니임 오일", "BT 살포"],
    "companion_plants": ["호박", "완두콩"],
    "incompatible_plants": ["토마토"],
    "special_care_tips": "작물이 크면 지지대를 사용해 지지",
    "regional_info": "따뜻한 기온을 선호",
    "reference_link": "https://www.gardeningknowhow.com/edible/vegetables/corn/growing-corn.htm"
  },
  {
    "name": "비트",
    "scientific_name": "Beta vulgaris",
    "image_url": "/assets/images/plants/비트.jpg",
    "growing_zone": "2-10",
    "max_height": "30 cm",
    "max_width": "15 cm",
    "sunlight_requirements": "부분 햇빛에서 완전한 햇빛",
    "sunlight_requirements_percent": 80,
    "water_requirements": "중간",
    "water_requirements_percent": 60,
    "soil_type": "양토",
    "pH_range": "6.0-7.0",
    "pH_range_percent": 85,
    "planting_time": {"months": [8, 9]},
    "harvest_time": "가을",
    "optimal_temperature": {"low": 10, "high": 20},
    "germination_period_percent": 75,
    "growth_rate_percent": 80,
    "common_pests": ["진딧물", "무파리"],
    "pest_control_methods": ["니임 오일", "파리 덫"],
    "companion_plants": ["상추", "양파"],
    "incompatible_plants": ["시금치"],
    "special_care_tips": "균일한 수분 공급을 유지",
    "regional_info": "서늘한 기온을 선호",
    "reference_link": "https://www.gardeningknowhow.com/edible/vegetables/beets/growing-beets.htm"
  },
  {
    "name": "양배추",
    "scientific_name": "Brassica oleracea var. capitata",
    "image_url": "/assets/images/plants/양배추.jpg",
    "growing_zone": "3-9",
    "max_height": "40 cm",
    "max_width": "60 cm",
    "sunlight_requirements": "완전한 햇빛",
    "sunlight_requirements_percent": 100,
    "water_requirements": "중간",
    "water_requirements_percent": 65,
    "soil_type": "양토",
    "pH_range": "6.0-7.5",
    "pH_range_percent": 80,
    "planting_time": {"months": [3, 7]},
    "harvest_time": "겨울",
    "optimal_temperature": {"low": 15, "high": 25},
    "germination_period_percent": 70,
    "growth_rate_percent": 75,
    "common_pests": ["배추벌레", "진딧물"],
    "pest_control_methods": ["니임 오일", "BT 살포"],
    "companion_plants": ["양파", "당근"],
    "incompatible_plants": ["토마토"],
    "special_care_tips": "잎과 줄기가 부드럽게 유지되도록 꾸준히 물 공급",
    "regional_info": "서늘한 기온을 선호",
    "reference_link": "https://www.nongsaro.go.kr/portal/ps/psz/psza/contentSub.ps?menuId=PS03172&pageIndex=1&pageSize=10&sSeCode=335001&cntntsNo=101619&sType=sCntntsSj&sText=%EC%96%91%EB%B0%B0%EC%B6%94"
  },
  {
    "name": "마늘",
    "scientific_name": "Allium sativum",
    "image_url": "/assets/images/plants/마늘.jpg",
    "growing_zone": "3-9",
    "max_height": "60 cm",
    "max_width": "15 cm",
    "sunlight_requirements": "완전한 햇빛",
    "sunlight_requirements_percent": 100,
    "water_requirements": "중간",
    "water_requirements_percent": 60,
    "soil_type": "양토",
    "pH_range": "6.0-7.0",
    "pH_range_percent": 85,
    "planting_time": {"months": [9, 10]},
    "harvest_time": "봄",
    "optimal_temperature": {"low": 10, "high": 25},
    "germination_period_percent": 70,
    "growth_rate_percent": 75,
    "common_pests": ["진딧물", "응애"],
    "pest_control_methods": ["니임 오일", "비누 스프레이"],
    "companion_plants": ["당근", "상추"],
    "incompatible_plants": ["콩"],
    "special_care_tips": "토양이 건조하지 않도록 주의",
    "regional_info": "서늘한 기온에서 잘 자람",
    "reference_link": "https://www.nongsaro.go.kr/portal/ps/psz/psza/contentSub.ps?menuId=PS03172&pageIndex=1&pageSize=10&sSeCode=335001&cntntsNo=101640&sType=sCntntsSj&sText=%EB%A7%88%EB%8A%98"
  },
  {
    "name": "딸기",
    "scientific_name": "Fragaria × ananassa",
    "image_url": "/assets/images/plants/딸기.jpg",
    "growing_zone": "4-8",
    "max_height": "30 cm",
    "max_width": "50 cm",
    "sunlight_requirements": "완전한 햇빛",
    "sunlight_requirements_percent": 100,
    "water_requirements": "중간",
    "water_requirements_percent": 60,
    "soil_type": "양토",
    "pH_range": "5.5-6.8",
    "pH_range_percent": 85,
    "planting_time": {"months": [3, 4, 9]},
    "harvest_time": "봄, 여름",
    "optimal_temperature": {"low": 15, "high": 25},
    "germination_period_percent": 70,
    "growth_rate_percent": 75,
    "common_pests": ["진딧물", "응애"],
    "pest_control_methods": ["니임 오일", "비누 스프레이"],
    "companion_plants": ["양파", "상추"],
    "incompatible_plants": ["양배추"],
    "special_care_tips": "과실이 닿는 부분에 짚을 깔아 과실 부패를 방지",
    "regional_info": "따뜻한 기온을 선호하며, 서늘한 봄과 가을에 잘 자람",
    "reference_link": "https://www.nongsaro.go.kr/portal/ps/psz/psza/contentSub.ps?menuId=PS03172&pageIndex=1&pageSize=10&sSeCode=335001&cntntsNo=101593&sType=sCntntsSj&sText=%EB%94%B8%EA%B8%B0"
  },
  {
    "name": "참외",
    "scientific_name": "Cucumis melo var. makuwa",
    "image_url": "/assets/images/plants/참외.jpg",
    "growing_zone": "6-9",
    "max_height": "30 cm",
    "max_width": "150 cm",
    "sunlight_requirements": "완전한 햇빛",
    "sunlight_requirements_percent": 100,
    "water_requirements": "중간",
    "water_requirements_percent": 70,
    "soil_type": "양토",
    "pH_range": "6.0-6.8",
    "pH_range_percent": 80,
    "planting_time": {"months": [4, 5]},
    "harvest_time": "여름",
    "optimal_temperature": {"low": 20, "high": 30},
    "germination_period_percent": 75,
    "growth_rate_percent": 80,
    "common_pests": ["진딧물", "응애"],
    "pest_control_methods": ["니임 오일", "비누 스프레이"],
    "companion_plants": ["옥수수", "상추"],
    "incompatible_plants": ["감자"],
    "special_care_tips": "덩굴이 잘 뻗을 수 있도록 충분한 공간 확보",
    "regional_info": "따뜻한 기온을 선호하며, 여름철에 잘 자람",
    "reference_link": "https://www.nongsaro.go.kr/portal/ps/psz/psza/contentSub.ps?menuId=PS03172&pageIndex=1&pageSize=10&sSeCode=335001&cntntsNo=101623&sType=sCntntsSj&sText=%EC%B0%B8%EC%99%B8"
  },
  {
    "name": "수박",
    "scientific_name": "Citrullus lanatus",
    "image_url": "/assets/images/plants/수박.jpg",
    "growing_zone": "3-11",
    "max_height": "30 cm",
    "max_width": "300 cm",
    "sunlight_requirements": "완전한 햇빛",
    "sunlight_requirements_percent": 100,
    "water_requirements": "중간",
    "water_requirements_percent": 70,
    "soil_type": "양토",
    "pH_range": "6.0-6.8",
    "pH_range_percent": 80,
    "planting_time": {"months": [4, 5]},
    "harvest_time": "여름",
    "optimal_temperature": {"low": 20, "high": 30},
    "germination_period_percent": 75,
    "growth_rate_percent": 85,
    "common_pests": ["진딧물", "응애"],
    "pest_control_methods": ["니임 오일", "비누 스프레이"],
    "companion_plants": ["옥수수", "호박"],
    "incompatible_plants": ["감자"],
    "special_care_tips": "덩굴이 잘 뻗을 수 있도록 충분한 공간 확보",
    "regional_info": "따뜻한 기온을 선호하며, 여름철에 잘 자람",
    "reference_link": "https://www.nongsaro.go.kr/portal/ps/psz/psza/contentSub.ps?menuId=PS03172&pageIndex=1&pageSize=10&sSeCode=335001&cntntsNo=101617&sType=sCntntsSj&sText=%EC%88%98%EB%B0%95"
  }
]